quikui/__init__.py
quikui/components.py
quikui/decorators.py
quikui/dependencies.py
quikui/exceptions.py
quikui/py.typed
quikui/sse.py
quikui/types.py
quikui/utils.py
quikui/templates/Anchor.html
quikui/templates/CheckboxInput.html
quikui/templates/FormInput.html
quikui/templates/Image.html
quikui/templates/RadioInput.html
quikui/templates/SelectionInput.html
quikui/templates/_MultiItemComponent.html
quikui/templates/_SingleContentComponent.html
quikui-0.3.0.dist-info/licenses/LICENSE
quikui-0.3.0.dist-info/METADATA
quikui-0.3.0.dist-info/WHEEL
quikui-0.3.0.dist-info/top_level.txt
quikui-0.3.0.dist-info/RECORD
