Metadata-Version: 2.4
Name: QuikUI
Version: 0.3.0
Summary: Build UIs quickly with Jinga2, FastAPI, Pydantic, htmx, and a little bit of magic
Author-email: "ApeWorX LTD." <admin@apeworx.io>
Classifier: Development Status :: 3 - Alpha
Classifier: Intended Audience :: Developers
Classifier: License :: OSI Approved :: Apache Software License
Classifier: Programming Language :: Python :: 3.10
Classifier: Programming Language :: Python :: 3.11
Classifier: Programming Language :: Python :: 3.12
Requires-Python: <4,>=3.10
License-File: LICENSE
Requires-Dist: fastapi[all]<1,>=0.100
Requires-Dist: Jinja2<4,>=3.0
Requires-Dist: pydantic<3,>=2.1
Provides-Extra: lint
Requires-Dist: black; extra == "lint"
Provides-Extra: test
Requires-Dist: pytest; extra == "test"
Provides-Extra: release
Requires-Dist: setuptools_scm; extra == "release"
Requires-Dist: wheel; extra == "release"
Provides-Extra: dev
Requires-Dist: IPython; extra == "dev"
Requires-Dist: quikui[lint,release,test]; extra == "dev"
Dynamic: license-file
